{
    "__module.model.layers.0.self_attn.v_proj/aten::linear/MatMul_160": 6.830548925044713e-06,
    "__module.model.layers.0.self_attn.k_proj/aten::linear/MatMul_159": 0.004870292865804736,
    "__module.model.layers.0.self_attn.q_proj/aten::linear/MatMul_158": 0.004153571586198927,
    "__module.model.layers.0.self_attn.o_proj/aten::linear/MatMul_346": 2.050952006738495e-06,
    "__module.model.layers.0.mlp.up_proj/aten::linear/MatMul_348": 0.00024021815635688834,
    "__module.model.layers.0.mlp.gate_proj/aten::linear/MatMul_347": 0.0003434975996183824,
    "__module.model.layers.0.mlp.down_proj/aten::linear/MatMul_349": 5.080479412680063e-06,
    "__module.model.layers.1.self_attn.v_proj/aten::linear/MatMul_358": 3.8762840530119104e-05,
    "__module.model.layers.1.self_attn.k_proj/aten::linear/MatMul_357": 0.020975330126487658,
    "__module.model.layers.1.self_attn.q_proj/aten::linear/MatMul_356": 0.01566109738950672,
    "__module.model.layers.1.self_attn.o_proj/aten::linear/MatMul_547": 1.5013296107923296e-06,
    "__module.model.layers.1.mlp.up_proj/aten::linear/MatMul_549": 0.0003756924537558665,
    "__module.model.layers.1.mlp.gate_proj/aten::linear/MatMul_548": 0.0005105029301450922,
    "__module.model.layers.1.mlp.down_proj/aten::linear/MatMul_550": 0.00016678254117695622,
    "__module.model.layers.2.self_attn.v_proj/aten::linear/MatMul_559": 0.0006829092157597652,
    "__module.model.layers.2.self_attn.k_proj/aten::linear/MatMul_558": 0.05267720427533796,
    "__module.model.layers.2.self_attn.q_proj/aten::linear/MatMul_557": 0.022457130072480954,
    "__module.model.layers.2.self_attn.o_proj/aten::linear/MatMul_748": 6.524798869022518e-06,
    "__module.model.layers.2.mlp.up_proj/aten::linear/MatMul_750": 0.0005353189119307177,
    "__module.model.layers.2.mlp.gate_proj/aten::linear/MatMul_749": 0.0008265491532812638,
    "__module.model.layers.2.mlp.down_proj/aten::linear/MatMul_751": 1.0431291709281478e-05,
    "__module.model.layers.3.self_attn.v_proj/aten::linear/MatMul_760": 0.0015273954784021202,
    "__module.model.layers.3.self_attn.k_proj/aten::linear/MatMul_759": 0.04571460943104299,
    "__module.model.layers.3.self_attn.q_proj/aten::linear/MatMul_758": 0.028174403507367347,
    "__module.model.layers.3.self_attn.o_proj/aten::linear/MatMul_949": 6.605706145366629e-05,
    "__module.model.layers.3.mlp.up_proj/aten::linear/MatMul_951": 0.0008601306841381139,
    "__module.model.layers.3.mlp.gate_proj/aten::linear/MatMul_950": 0.0013903907232492062,
    "__module.model.layers.3.mlp.down_proj/aten::linear/MatMul_952": 0.04091160686711028,
    "__module.model.layers.4.self_attn.v_proj/aten::linear/MatMul_961": 0.0025737740808109565,
    "__module.model.layers.4.self_attn.k_proj/aten::linear/MatMul_960": 0.06339895998786714,
    "__module.model.layers.4.self_attn.q_proj/aten::linear/MatMul_959": 0.04248923503803714,
    "__module.model.layers.4.self_attn.o_proj/aten::linear/MatMul_1150": 2.8472574230095844e-05,
    "__module.model.layers.4.mlp.up_proj/aten::linear/MatMul_1152": 0.0011698600095896457,
    "__module.model.layers.4.mlp.gate_proj/aten::linear/MatMul_1151": 0.0019858749827982355,
    "__module.model.layers.4.mlp.down_proj/aten::linear/MatMul_1153": 3.0011762663163862e-05,
    "__module.model.layers.5.self_attn.v_proj/aten::linear/MatMul_1162": 0.0035644035830256415,
    "__module.model.layers.5.self_attn.k_proj/aten::linear/MatMul_1161": 0.05966363916261944,
    "__module.model.layers.5.self_attn.q_proj/aten::linear/MatMul_1160": 0.04053057172951953,
    "__module.model.layers.5.self_attn.o_proj/aten::linear/MatMul_1351": 2.2039835788280104e-05,
    "__module.model.layers.5.mlp.up_proj/aten::linear/MatMul_1353": 0.0015981477045038245,
    "__module.model.layers.5.mlp.gate_proj/aten::linear/MatMul_1352": 0.003297078983557226,
    "__module.model.layers.5.mlp.down_proj/aten::linear/MatMul_1354": 4.169106952443783e-05,
    "__module.model.layers.6.self_attn.v_proj/aten::linear/MatMul_1363": 0.003587880956517898,
    "__module.model.layers.6.self_attn.k_proj/aten::linear/MatMul_1362": 0.055042399415362646,
    "__module.model.layers.6.self_attn.q_proj/aten::linear/MatMul_1361": 0.03532842454481685,
    "__module.model.layers.6.self_attn.o_proj/aten::linear/MatMul_1552": 2.703759175154614e-05,
    "__module.model.layers.6.mlp.up_proj/aten::linear/MatMul_1554": 0.0020117671826138882,
    "__module.model.layers.6.mlp.gate_proj/aten::linear/MatMul_1553": 0.005289347516176219,
    "__module.model.layers.6.mlp.down_proj/aten::linear/MatMul_1555": 0.0003694640560642705,
    "__module.model.layers.7.self_attn.v_proj/aten::linear/MatMul_1564": 0.0039362044906208985,
    "__module.model.layers.7.self_attn.k_proj/aten::linear/MatMul_1563": 0.056496394869277475,
    "__module.model.layers.7.self_attn.q_proj/aten::linear/MatMul_1562": 0.037031042416605146,
    "__module.model.layers.7.self_attn.o_proj/aten::linear/MatMul_1753": 4.013325888721475e-05,
    "__module.model.layers.7.mlp.up_proj/aten::linear/MatMul_1755": 0.0022898778919429024,
    "__module.model.layers.7.mlp.gate_proj/aten::linear/MatMul_1754": 0.006368750584318897,
    "__module.model.layers.7.mlp.down_proj/aten::linear/MatMul_1756": 8.220398839185688e-05,
    "__module.model.layers.8.self_attn.v_proj/aten::linear/MatMul_1765": 0.00398202247954866,
    "__module.model.layers.8.self_attn.k_proj/aten::linear/MatMul_1764": 0.05877402203623005,
    "__module.model.layers.8.self_attn.q_proj/aten::linear/MatMul_1763": 0.04013181817332333,
    "__module.model.layers.8.self_attn.o_proj/aten::linear/MatMul_1954": 5.719062380454954e-05,
    "__module.model.layers.8.mlp.up_proj/aten::linear/MatMul_1956": 0.002661170863093024,
    "__module.model.layers.8.mlp.gate_proj/aten::linear/MatMul_1955": 0.005180485754435945,
    "__module.model.layers.8.mlp.down_proj/aten::linear/MatMul_1957": 9.685857234131718e-05,
    "__module.model.layers.9.self_attn.v_proj/aten::linear/MatMul_1966": 0.004768466327363935,
    "__module.model.layers.9.self_attn.k_proj/aten::linear/MatMul_1965": 0.04963901405879209,
    "__module.model.layers.9.self_attn.q_proj/aten::linear/MatMul_1964": 0.037806792151761866,
    "__module.model.layers.9.self_attn.o_proj/aten::linear/MatMul_2155": 5.7694649437195726e-05,
    "__module.model.layers.9.mlp.up_proj/aten::linear/MatMul_2157": 0.002900120939465449,
    "__module.model.layers.9.mlp.gate_proj/aten::linear/MatMul_2156": 0.0049086924774553705,
    "__module.model.layers.9.mlp.down_proj/aten::linear/MatMul_2158": 0.0001078682824201656,
    "__module.model.layers.10.self_attn.v_proj/aten::linear/MatMul_2167": 0.005705003438651045,
    "__module.model.layers.10.self_attn.k_proj/aten::linear/MatMul_2166": 0.05048408101287854,
    "__module.model.layers.10.self_attn.q_proj/aten::linear/MatMul_2165": 0.03668905641946603,
    "__module.model.layers.10.self_attn.o_proj/aten::linear/MatMul_2356": 8.183893522869836e-05,
    "__module.model.layers.10.mlp.up_proj/aten::linear/MatMul_2358": 0.0032346432395604324,
    "__module.model.layers.10.mlp.gate_proj/aten::linear/MatMul_2357": 0.005053093762387114,
    "__module.model.layers.10.mlp.down_proj/aten::linear/MatMul_2359": 0.00013479786474793144,
    "__module.model.layers.11.self_attn.v_proj/aten::linear/MatMul_2368": 0.006179209475032566,
    "__module.model.layers.11.self_attn.k_proj/aten::linear/MatMul_2367": 0.052253477452162606,
    "__module.model.layers.11.self_attn.q_proj/aten::linear/MatMul_2366": 0.04344663074331476,
    "__module.model.layers.11.self_attn.o_proj/aten::linear/MatMul_2557": 9.637755561472529e-05,
    "__module.model.layers.11.mlp.up_proj/aten::linear/MatMul_2559": 0.0035502971000403315,
    "__module.model.layers.11.mlp.gate_proj/aten::linear/MatMul_2558": 0.005271642489428694,
    "__module.model.layers.11.mlp.down_proj/aten::linear/MatMul_2560": 0.0001539973450967742,
    "__module.model.layers.12.self_attn.v_proj/aten::linear/MatMul_2569": 0.0065278517165139605,
    "__module.model.layers.12.self_attn.k_proj/aten::linear/MatMul_2568": 0.052121902291968676,
    "__module.model.layers.12.self_attn.q_proj/aten::linear/MatMul_2567": 0.037294332044941994,
    "__module.model.layers.12.self_attn.o_proj/aten::linear/MatMul_2758": 0.00011247414295234603,
    "__module.model.layers.12.mlp.up_proj/aten::linear/MatMul_2760": 0.003694941473456298,
    "__module.model.layers.12.mlp.gate_proj/aten::linear/MatMul_2759": 0.004834707728200589,
    "__module.model.layers.12.mlp.down_proj/aten::linear/MatMul_2761": 0.00016397325701908563,
    "__module.model.layers.13.self_attn.v_proj/aten::linear/MatMul_2770": 0.009001103292921872,
    "__module.model.layers.13.self_attn.k_proj/aten::linear/MatMul_2769": 0.04652667098250228,
    "__module.model.layers.13.self_attn.q_proj/aten::linear/MatMul_2768": 0.036589353970081354,
    "__module.model.layers.13.self_attn.o_proj/aten::linear/MatMul_2959": 9.845740376781346e-05,
    "__module.model.layers.13.mlp.up_proj/aten::linear/MatMul_2961": 0.0038585514087858624,
    "__module.model.layers.13.mlp.gate_proj/aten::linear/MatMul_2960": 0.005340966291903481,
    "__module.model.layers.13.mlp.down_proj/aten::linear/MatMul_2962": 0.00017605737472857136,
    "__module.model.layers.14.self_attn.v_proj/aten::linear/MatMul_2971": 0.0065291998213030025,
    "__module.model.layers.14.self_attn.k_proj/aten::linear/MatMul_2970": 0.06093813067646591,
    "__module.model.layers.14.self_attn.q_proj/aten::linear/MatMul_2969": 0.04269695973905286,
    "__module.model.layers.14.self_attn.o_proj/aten::linear/MatMul_3160": 0.0001597911587148456,
    "__module.model.layers.14.mlp.up_proj/aten::linear/MatMul_3162": 0.0042379210333500505,
    "__module.model.layers.14.mlp.gate_proj/aten::linear/MatMul_3161": 0.0051812023221596264,
    "__module.model.layers.14.mlp.down_proj/aten::linear/MatMul_3163": 0.0002254843999572662,
    "__module.model.layers.15.self_attn.v_proj/aten::linear/MatMul_3172": 0.008354547966159327,
    "__module.model.layers.15.self_attn.k_proj/aten::linear/MatMul_3171": 0.05405653652676556,
    "__module.model.layers.15.self_attn.q_proj/aten::linear/MatMul_3170": 0.03815929447529646,
    "__module.model.layers.15.self_attn.o_proj/aten::linear/MatMul_3361": 0.00014170106422004312,
    "__module.model.layers.15.mlp.up_proj/aten::linear/MatMul_3363": 0.004800178206784333,
    "__module.model.layers.15.mlp.gate_proj/aten::linear/MatMul_3362": 0.005105628269857063,
    "__module.model.layers.15.mlp.down_proj/aten::linear/MatMul_3364": 0.00027223800026847383,
    "__module.model.layers.16.self_attn.v_proj/aten::linear/MatMul_3373": 0.008071536203995344,
    "__module.model.layers.16.self_attn.k_proj/aten::linear/MatMul_3372": 0.058022425744181975,
    "__module.model.layers.16.self_attn.q_proj/aten::linear/MatMul_3371": 0.038030598226466435,
    "__module.model.layers.16.self_attn.o_proj/aten::linear/MatMul_3562": 0.00017964104318722566,
    "__module.model.layers.16.mlp.up_proj/aten::linear/MatMul_3564": 0.005023216236177722,
    "__module.model.layers.16.mlp.gate_proj/aten::linear/MatMul_3563": 0.005286295146357116,
    "__module.model.layers.16.mlp.down_proj/aten::linear/MatMul_3565": 0.00030449735196585526,
    "__module.model.layers.17.self_attn.v_proj/aten::linear/MatMul_3574": 0.009504851595942781,
    "__module.model.layers.17.self_attn.k_proj/aten::linear/MatMul_3573": 0.05684497532233231,
    "__module.model.layers.17.self_attn.q_proj/aten::linear/MatMul_3572": 0.03843577590777814,
    "__module.model.layers.17.self_attn.o_proj/aten::linear/MatMul_3763": 0.00016005324403369314,
    "__module.model.layers.17.mlp.up_proj/aten::linear/MatMul_3765": 0.005319497737093308,
    "__module.model.layers.17.mlp.gate_proj/aten::linear/MatMul_3764": 0.0057336655109185225,
    "__module.model.layers.17.mlp.down_proj/aten::linear/MatMul_3766": 0.0003899935151779858,
    "__module.model.layers.18.self_attn.v_proj/aten::linear/MatMul_3775": 0.009561513283109006,
    "__module.model.layers.18.self_attn.k_proj/aten::linear/MatMul_3774": 0.05674298169346802,
    "__module.model.layers.18.self_attn.q_proj/aten::linear/MatMul_3773": 0.038162113634428625,
    "__module.model.layers.18.self_attn.o_proj/aten::linear/MatMul_3964": 0.00014927158432049707,
    "__module.model.layers.18.mlp.up_proj/aten::linear/MatMul_3966": 0.005440889626662185,
    "__module.model.layers.18.mlp.gate_proj/aten::linear/MatMul_3965": 0.006163972612477128,
    "__module.model.layers.18.mlp.down_proj/aten::linear/MatMul_3967": 0.0004232250152128248,
    "__module.model.layers.19.self_attn.v_proj/aten::linear/MatMul_3976": 0.010100071538576273,
    "__module.model.layers.19.self_attn.k_proj/aten::linear/MatMul_3975": 0.0554365892457389,
    "__module.model.layers.19.self_attn.q_proj/aten::linear/MatMul_3974": 0.040389904014064296,
    "__module.model.layers.19.self_attn.o_proj/aten::linear/MatMul_4165": 0.0001632562210809608,
    "__module.model.layers.19.mlp.up_proj/aten::linear/MatMul_4167": 0.00573203577921755,
    "__module.model.layers.19.mlp.gate_proj/aten::linear/MatMul_4166": 0.007067657449259716,
    "__module.model.layers.19.mlp.down_proj/aten::linear/MatMul_4168": 0.0004977383853839151,
    "__module.model.layers.20.self_attn.v_proj/aten::linear/MatMul_4177": 0.010836894495411222,
    "__module.model.layers.20.self_attn.k_proj/aten::linear/MatMul_4176": 0.052377664107868385,
    "__module.model.layers.20.self_attn.q_proj/aten::linear/MatMul_4175": 0.04092104590071221,
    "__module.model.layers.20.self_attn.o_proj/aten::linear/MatMul_4366": 0.00014884522414298303,
    "__module.model.layers.20.mlp.up_proj/aten::linear/MatMul_4368": 0.005933861715105503,
    "__module.model.layers.20.mlp.gate_proj/aten::linear/MatMul_4367": 0.007448732401439618,
    "__module.model.layers.20.mlp.down_proj/aten::linear/MatMul_4369": 0.0005274231810104653,
    "__module.model.layers.21.self_attn.v_proj/aten::linear/MatMul_4378": 0.010849447880325989,
    "__module.model.layers.21.self_attn.k_proj/aten::linear/MatMul_4377": 0.06231777446592519,
    "__module.model.layers.21.self_attn.q_proj/aten::linear/MatMul_4376": 0.04473765952800702,
    "__module.model.layers.21.self_attn.o_proj/aten::linear/MatMul_4567": 0.00024127580947566393,
    "__module.model.layers.21.mlp.up_proj/aten::linear/MatMul_4569": 0.006568988368070456,
    "__module.model.layers.21.mlp.gate_proj/aten::linear/MatMul_4568": 0.008321208675449733,
    "__module.model.layers.21.mlp.down_proj/aten::linear/MatMul_4570": 0.0006365898885340056,
    "__module.model.layers.22.self_attn.v_proj/aten::linear/MatMul_4579": 0.012590093524923046,
    "__module.model.layers.22.self_attn.k_proj/aten::linear/MatMul_4578": 0.05495956940542222,
    "__module.model.layers.22.self_attn.q_proj/aten::linear/MatMul_4577": 0.042096450491678226,
    "__module.model.layers.22.self_attn.o_proj/aten::linear/MatMul_4768": 0.00021463841249881865,
    "__module.model.layers.22.mlp.up_proj/aten::linear/MatMul_4770": 0.0069478590028102406,
    "__module.model.layers.22.mlp.gate_proj/aten::linear/MatMul_4769": 0.008612112468000767,
    "__module.model.layers.22.mlp.down_proj/aten::linear/MatMul_4771": 0.0007018573254366162,
    "__module.model.layers.23.self_attn.v_proj/aten::linear/MatMul_4780": 0.012926817642787043,
    "__module.model.layers.23.self_attn.k_proj/aten::linear/MatMul_4779": 0.06207560897433933,
    "__module.model.layers.23.self_attn.q_proj/aten::linear/MatMul_4778": 0.04619160891547256,
    "__module.model.layers.23.self_attn.o_proj/aten::linear/MatMul_4969": 0.00034653119137001274,
    "__module.model.layers.23.mlp.up_proj/aten::linear/MatMul_4971": 0.0076785794167423625,
    "__module.model.layers.23.mlp.gate_proj/aten::linear/MatMul_4970": 0.009148142810713945,
    "__module.model.layers.23.mlp.down_proj/aten::linear/MatMul_4972": 0.0009385424311846477,
    "__module.model.layers.24.self_attn.v_proj/aten::linear/MatMul_4981": 0.013104247388487634,
    "__module.model.layers.24.self_attn.k_proj/aten::linear/MatMul_4980": 0.057222662284042665,
    "__module.model.layers.24.self_attn.q_proj/aten::linear/MatMul_4979": 0.040084589324989,
    "__module.model.layers.24.self_attn.o_proj/aten::linear/MatMul_5170": 0.00015219856673400752,
    "__module.model.layers.24.mlp.up_proj/aten::linear/MatMul_5172": 0.007967144697152172,
    "__module.model.layers.24.mlp.gate_proj/aten::linear/MatMul_5171": 0.009456536514014867,
    "__module.model.layers.24.mlp.down_proj/aten::linear/MatMul_5173": 0.0010158840038254405,
    "__module.model.layers.25.self_attn.v_proj/aten::linear/MatMul_5182": 0.015765045396243835,
    "__module.model.layers.25.self_attn.k_proj/aten::linear/MatMul_5181": 0.05368531276102288,
    "__module.model.layers.25.self_attn.q_proj/aten::linear/MatMul_5180": 0.042240736644249675,
    "__module.model.layers.25.self_attn.o_proj/aten::linear/MatMul_5371": 0.00028110125318701125,
    "__module.model.layers.25.mlp.up_proj/aten::linear/MatMul_5373": 0.008642285085245808,
    "__module.model.layers.25.mlp.gate_proj/aten::linear/MatMul_5372": 0.00970493648604833,
    "__module.model.layers.25.mlp.down_proj/aten::linear/MatMul_5374": 0.001140672308966019,
    "__module.model.layers.26.self_attn.v_proj/aten::linear/MatMul_5383": 0.016618970782991613,
    "__module.model.layers.26.self_attn.k_proj/aten::linear/MatMul_5382": 0.05468960279771805,
    "__module.model.layers.26.self_attn.q_proj/aten::linear/MatMul_5381": 0.04091660485475732,
    "__module.model.layers.26.self_attn.o_proj/aten::linear/MatMul_5572": 0.0004645699894076626,
    "__module.model.layers.26.mlp.up_proj/aten::linear/MatMul_5574": 0.009057007302699318,
    "__module.model.layers.26.mlp.gate_proj/aten::linear/MatMul_5573": 0.00978857158773367,
    "__module.model.layers.26.mlp.down_proj/aten::linear/MatMul_5575": 0.0012986711445423418,
    "__module.model.layers.27.self_attn.v_proj/aten::linear/MatMul_5584": 0.017147742407467064,
    "__module.model.layers.27.self_attn.k_proj/aten::linear/MatMul_5583": 0.053618111859888025,
    "__module.model.layers.27.self_attn.q_proj/aten::linear/MatMul_5582": 0.03904437264397552,
    "__module.model.layers.27.self_attn.o_proj/aten::linear/MatMul_5773": 0.00040142171953804,
    "__module.model.layers.27.mlp.up_proj/aten::linear/MatMul_5775": 0.009563276670044484,
    "__module.model.layers.27.mlp.gate_proj/aten::linear/MatMul_5774": 0.00988460701109583,
    "__module.model.layers.27.mlp.down_proj/aten::linear/MatMul_5776": 0.001358426304381338,
    "__module.model.layers.28.self_attn.v_proj/aten::linear/MatMul_5785": 0.019159453358262035,
    "__module.model.layers.28.self_attn.k_proj/aten::linear/MatMul_5784": 0.05042834429888466,
    "__module.model.layers.28.self_attn.q_proj/aten::linear/MatMul_5783": 0.03809004288371688,
    "__module.model.layers.28.self_attn.o_proj/aten::linear/MatMul_5974": 0.0006176743502310229,
    "__module.model.layers.28.mlp.up_proj/aten::linear/MatMul_5976": 0.010486393225906023,
    "__module.model.layers.28.mlp.gate_proj/aten::linear/MatMul_5975": 0.011177216270135947,
    "__module.model.layers.28.mlp.down_proj/aten::linear/MatMul_5977": 0.0015134333608961632,
    "__module.model.layers.29.self_attn.v_proj/aten::linear/MatMul_5986": 0.01728749627670547,
    "__module.model.layers.29.self_attn.k_proj/aten::linear/MatMul_5985": 0.05584602580743627,
    "__module.model.layers.29.self_attn.q_proj/aten::linear/MatMul_5984": 0.036897528985515834,
    "__module.model.layers.29.self_attn.o_proj/aten::linear/MatMul_6175": 0.0007945371492911437,
    "__module.model.layers.29.mlp.up_proj/aten::linear/MatMul_6177": 0.013543358240196325,
    "__module.model.layers.29.mlp.gate_proj/aten::linear/MatMul_6176": 0.015312610335333517,
    "__module.model.layers.29.mlp.down_proj/aten::linear/MatMul_6178": 0.0033691938743057085,
    "__module.model.layers.30.self_attn.v_proj/aten::linear/MatMul_6187": 0.020399515589291258,
    "__module.model.layers.30.self_attn.k_proj/aten::linear/MatMul_6186": 0.05472478490793876,
    "__module.model.layers.30.self_attn.q_proj/aten::linear/MatMul_6185": 0.039881895867722256,
    "__module.model.layers.30.self_attn.o_proj/aten::linear/MatMul_6376": 0.0017732042647721324,
    "__module.model.layers.30.mlp.up_proj/aten::linear/MatMul_6378": 0.023362237781375198,
    "__module.model.layers.30.mlp.gate_proj/aten::linear/MatMul_6377": 0.02380501859766413,
    "__module.model.layers.30.mlp.down_proj/aten::linear/MatMul_6379": 0.0032336674415183444,
    "__module.model.layers.31.self_attn.v_proj/aten::linear/MatMul_6388": 0.018842677023945768,
    "__module.model.layers.31.self_attn.k_proj/aten::linear/MatMul_6387": 0.05807040554772711,
    "__module.model.layers.31.self_attn.q_proj/aten::linear/MatMul_6386": 0.03664391519334022,
    "__module.model.layers.31.self_attn.o_proj/aten::linear/MatMul_6577": 0.009184991003884086,
    "__module.model.layers.31.mlp.up_proj/aten::linear/MatMul_6579": 0.030818759802296057,
    "__module.model.layers.31.mlp.gate_proj/aten::linear/MatMul_6578": 0.02603665599551239,
    "__module.model.layers.31.mlp.down_proj/aten::linear/MatMul_6580": 0.021046957283370953
}